promethium/__about__.py
promethium/__init__.py
promethium/distributions/binomial.py
promethium/distributions/chi2.py
promethium/distributions/geometric.py
promethium/distributions/normal.py
promethium/distributions/poisson.py
promethium/special/gamma.py
promethium-0.7.6.dist-info/METADATA
promethium-0.7.6.dist-info/WHEEL
promethium-0.7.6.dist-info/licenses/LICENSE
promethium-0.7.6.dist-info/RECORD
