Metadata-Version: 2.4
Name: promethium
Version: 0.7.6
Summary: Library for calculating statistical distributions, written in pure Python with zero dependencies.
Project-URL: Documentation, https://github.com/ostromia/promethium/wiki/Documentation
Project-URL: Issues, https://github.com/berkay-yalin/promethium/issues
Project-URL: Source, https://github.com/berkay-yalin/promethium
Author-email: ostromia <66202981+ostromia@users.noreply.github.com>
License-Expression: MIT
License-File: LICENSE
Classifier: Development Status :: 4 - Beta
Classifier: Programming Language :: Python
Classifier: Programming Language :: Python :: 3.9
Classifier: Programming Language :: Python :: 3.10
Classifier: Programming Language :: Python :: 3.11
Classifier: Programming Language :: Python :: 3.12
Classifier: Programming Language :: Python :: Implementation :: CPython
Classifier: Programming Language :: Python :: Implementation :: PyPy
Classifier: Typing :: Typed
Requires-Python: >=3.9
